README.md
setup.py
seschtools/__init__.py
seschtools/read_file.py
seschtools.egg-info/PKG-INFO
seschtools.egg-info/SOURCES.txt
seschtools.egg-info/dependency_links.txt
seschtools.egg-info/requires.txt
seschtools.egg-info/top_level.txt