Metadata-Version: 2.1
Name: seschtools
Version: 0.2
Summary:  Reads Survey Data file and Returns it as Pandas DataFrame
Home-page: UNKNOWN
Author: Nitin Singh
Author-email: acc4nitin@gmail.com
License: MIT
Platform: UNKNOWN
Classifier: License :: OSI Approved :: MIT License
Classifier: Programming Language :: Python :: 3
Classifier: Programming Language :: Python :: 3.7
